Workbook

Sheet Income Statement
A1: PayPal Holdings - Income Statement ($ Millions)
B2: 2023 | C2: 2024 | D2: 2025
A3: Revenue | B3: 29771 | C3: 31797 | D3: 33172
A4: COGS | B4: 16067 | C4: 17139 | D4: 17707
A5: Gross Profit | B5: =B3-B4 -> 13704 | C5: =C3-C4 -> 14658 | D5: =D3-D4 -> 15465
A6: Operating Exp | B6: 8760 | C6: 8895 | D6: 9069
A7: EBIT | B7: =B5-B6 -> 4944 | C7: =C5-C6 -> 5763 | D7: =D5-D6 -> 6396
A8: Net Income | B8: 4246 | C8: 4147 | D8: 5233
A10: Gross Margin | B10: =B5/B3 -> 0.46031373 | C10: =C5/C3 -> 0.46098689 | D10: =D5/D3 -> 0.46620644
A11: Net Margin | B11: =B8/B3 -> 0.14262201 | C11: =C8/C3 -> 0.13042111 | D11: =D8/D3 -> 0.15775353
A12: EBIT Margin | B12: =B7/B3 -> 0.16606765 | C12: =C7/C3 -> 0.18124351 | D12: =D7/D3 -> 0.19281322

Sheet Balance Sheet
A1: PayPal Holdings - Balance Sheet ($ Millions)
B2: 2023 | C2: 2024 | D2: 2025
A3: Total Assets | B3: 82166 | C3: 78725 | D3: 80173
A4: Total Liabilities | B4: 61115 | C4: 58308 | D4: 59917
A5: Shareholders Equity | B5: =B3-B4 -> 21051 | C5: =C3-C4 -> 20417 | D5: =D3-D4 -> 20256
A6: Total Debt | B6: 9676 | C6: 9879 | D6: 9987
A7: Cash & Equivalent | B7: 9081 | C7: 6662 | D7: 8049
A9: Debt/Equity Ratio | B9: =B6/B5 -> 0.45964562 | C9: =C6/C5 -> 0.48386149 | D9: =D6/D5 -> 0.4930391
A10: Current Ratio

Sheet Cash Flow
A1: PayPal Holdings - Cash Flow ($ Millions)
B2: 2023 | C2: 2024 | D2: 2025
A3: Operating Cash Flow | B3: 4843 | C3: 7450 | D3: 6416
A4: Capital Expenditure | B4: 623 | C4: 683 | D4: 852
A5: Free Cash Flow | B5: =B3-B4 -> 4220 | C5: =C3-C4 -> 6767 | D5: =D3-D4 -> 5564
A7: FCF Margin | B7: =B5/'Income Statement'!B3 -> 0.14174868 | C7: =C5/'Income Statement'!C3 -> 0.21281882 | D7: =D5/'Income Statement'!D3 -> 0.16773182
A8: FCF Conversion | B8: =B5/'Income Statement'!B8 -> 0.99387659 | C8: =C5/'Income Statement'!C8 -> 1.631782 | D8: =D5/'Income Statement'!D8 -> 1.0632524

Sheet Summary
A1: PayPal Holdings - Financial Summary ($ Millions)
B2: 2023 | C2: 2024 | D2: 2025 | E2: Trend
A3: Revenue | B3: ='Income Statement'!B3 -> 29771 | C3: ='Income Statement'!C3 -> 31797 | D3: ='Income Statement'!D3 -> 33172 | E3: =D3/B3-1 -> 0.11423869
A4: Gross Margin | B4: ='Income Statement'!B10 -> 0.46031373 | C4: ='Income Statement'!C10 -> 0.46098689 | D4: ='Income Statement'!D10 -> 0.46620644 | E4: =D4/B4-1 -> 0.012801511
A5: EBIT Margin | B5: ='Income Statement'!B12 -> 0.16606765 | C5: ='Income Statement'!C12 -> 0.18124351 | D5: ='Income Statement'!D12 -> 0.19281322 | E5: =D5/B5-1 -> 0.16105224
A6: Net Margin | B6: ='Income Statement'!B11 -> 0.14262201 | C6: ='Income Statement'!C11 -> 0.13042111 | D6: ='Income Statement'!D11 -> 0.15775353 | E6: =D6/B6-1 -> 0.10609521
A7: FCF | B7: ='Cash Flow'!B5 -> 4220 | C7: ='Cash Flow'!C5 -> 6767 | D7: ='Cash Flow'!D5 -> 5564 | E7: =D7/B7-1 -> 0.31848341
A8: FCF Margin | B8: ='Cash Flow'!B7 -> 0.14174868 | C8: ='Cash Flow'!C7 -> 0.21281882 | D8: ='Cash Flow'!D7 -> 0.16773182 | E8: =D8/B8-1 -> 0.18330428
A9: Debt/Equity | B9: ='Balance Sheet'!B9 -> 0.45964562 | C9: ='Balance Sheet'!C9 -> 0.48386149 | D9: ='Balance Sheet'!D9 -> 0.4930391 | E9: =D9/B9-1 -> 0.072650484
